boundio/__init__.py
boundio/item_codes.py
boundio/stdin.py
boundio/asynchronous/__init__.py
boundio/asynchronous/queues.py
boundio/asynchronous/tasks.py
boundio/asynchronous/utils.py
boundio/asynchronous/raw_io/__init__.py
boundio/asynchronous/raw_io/files.py
boundio/asynchronous/raw_io/sockets.py
boundio/asynchronous/raw_io/stdin.py
boundio/examples/__init__.py
boundio/examples/stdin_simple.py
boundio/examples/utils.py
boundio/examples/websocket_simple.py
boundio/sockets/__init__.py
boundio/sockets/process.py
boundio/sockets/tasks.py
boundio/sockets/utils.py
tests/__init__.py
tests/global_vars_test.py
tests/import_test.py
boundio-0.0.2.dist-info/LICENSE
boundio-0.0.2.dist-info/METADATA
boundio-0.0.2.dist-info/WHEEL
boundio-0.0.2.dist-info/top_level.txt
boundio-0.0.2.dist-info/RECORD
