Metadata-Version: 2.1
Name: boundio
Version: 0.0.2
Summary: A toolkit for IO-bound applications.
Home-page: https://github.com/a1liu/boundio
Author: A1Liu
Author-email: albertymliu@gmail.com
License: UNKNOWN
Platform: UNKNOWN
Classifier: Programming Language :: Python :: 3.6
Classifier: Programming Language :: Python :: 3.7
Classifier: License :: OSI Approved :: Apache Software License
Classifier: Operating System :: OS Independent
Requires-Dist: aiofiles
Requires-Dist: websockets
Requires-Dist: aiohttp
Requires-Dist: cchardet
Requires-Dist: aiodns
